stash/__init__.py
stash/client.py
stash/errors.py
stash/types.py
stash/zk.py
stash_client-0.2.0.dist-info/METADATA
stash_client-0.2.0.dist-info/WHEEL
stash_client-0.2.0.dist-info/RECORD
