Metadata-Version: 2.4
Name: stash-client
Version: 0.2.0
Summary: Python client library for Stash - a simple key-value configuration service
Project-URL: Homepage, https://github.com/umputun/stash
Project-URL: Documentation, https://github.com/umputun/stash/tree/master/lib/stash-python
Project-URL: Repository, https://github.com/umputun/stash
Author: Umputun
License-Expression: MIT
Keywords: configuration,key-value,kv,stash
Classifier: Development Status :: 4 - Beta
Classifier: Intended Audience :: Developers
Classifier: License :: OSI Approved :: MIT License
Classifier: Operating System :: OS Independent
Classifier: Programming Language :: Python :: 3
Classifier: Programming Language :: Python :: 3.10
Classifier: Programming Language :: Python :: 3.11
Classifier: Programming Language :: Python :: 3.12
Classifier: Programming Language :: Python :: 3.13
Classifier: Topic :: Software Development :: Libraries :: Python Modules
Classifier: Typing :: Typed
Requires-Python: >=3.10
Requires-Dist: argon2-cffi>=23.0
Requires-Dist: cryptography>=41.0
Requires-Dist: sseclient-py>=1.8
Requires-Dist: urllib3>=2.0
Provides-Extra: dev
Requires-Dist: pytest-cov>=4.0; extra == 'dev'
Requires-Dist: pytest>=8.0; extra == 'dev'
Requires-Dist: responses>=0.25; extra == 'dev'
Requires-Dist: ruff>=0.4; extra == 'dev'
